logix.py
logix-1.0.4.dist-info/LICENSE
logix-1.0.4.dist-info/METADATA
logix-1.0.4.dist-info/WHEEL
logix-1.0.4.dist-info/top_level.txt
logix-1.0.4.dist-info/RECORD
